talksql/__init__.py
talksql/sqli.py
talksql-1.2.dist-info/METADATA
talksql-1.2.dist-info/WHEEL
talksql-1.2.dist-info/top_level.txt
talksql-1.2.dist-info/RECORD
