Metadata-Version: 2.1
Name: talksql
Version: 1.2
Summary: A utility package for sql work
Home-page: https://www.github.com/madhukumarseshadri/talkweb3
Author: Madhukumar Seshadri
Author-email: madhukumarseshadri@gmail.com
License: MIT License
Platform: any
Classifier: Development Status :: 5 - Production/Stable
Classifier: Environment :: Web Environment
Classifier: Intended Audience :: Developers
Classifier: License :: OSI Approved :: MIT License
Classifier: Operating System :: OS Independent
Classifier: Programming Language :: Python
Classifier: Topic :: Internet :: WWW/HTTP :: Dynamic Content
Classifier: Topic :: Software Development :: Libraries :: Python Modules
Classifier: Topic :: Software Development :: Libraries :: Application Frameworks
